ragora/__init__.py
ragora/_version.py
ragora/exceptions.py
ragora/version.py
ragora/cli/__init__.py
ragora/cli/main.py
ragora/config/__init__.py
ragora/config/settings.py
ragora/core/__init__.py
ragora/core/chunking.py
ragora/core/database_manager.py
ragora/core/document_preprocessor.py
ragora/core/email_preprocessor.py
ragora/core/embedding_engine.py
ragora/core/filters.py
ragora/core/knowledge_base_manager.py
ragora/core/models.py
ragora/core/retriever.py
ragora/core/vector_store.py
ragora/examples/__init__.py
ragora/examples/advanced_usage.py
ragora/examples/basic_usage.py
ragora/examples/email_usage_examples.py
ragora/examples/example.env
ragora/utils/__init__.py
ragora/utils/device_utils.py
ragora/utils/email_provider_factory.py
ragora/utils/latex_parser.py
ragora/utils/markdown_parser.py
ragora/utils/email_utils/__init__.py
ragora/utils/email_utils/base.py
ragora/utils/email_utils/graph_provider.py
ragora/utils/email_utils/imap_provider.py
ragora/utils/email_utils/models.py
ragora-1.3.0.dist-info/licenses/LICENSE
ragora-1.3.0.dist-info/METADATA
ragora-1.3.0.dist-info/WHEEL
ragora-1.3.0.dist-info/entry_points.txt
ragora-1.3.0.dist-info/top_level.txt
ragora-1.3.0.dist-info/RECORD
