Metadata-Version: 2.4
Name: ragora
Version: 1.3.0
Summary: A RAG system for creating knowledge bases from different document formats
Author-email: Vahid Lari <vahid.lari@gmail.com>
Maintainer-email: Vahid Lari <vahid.lari@gmail.com>
License-Expression: MIT
Project-URL: Homepage, https://github.com/vahidlari/aiapps
Project-URL: Repository, https://github.com/vahidlari/aiapps
Project-URL: Issues, https://github.com/vahidlari/aiapps/issues
Keywords: rag,retrieval-augmented-generation,nlp,machine-learning,vector-database,weaviate,embeddings
Classifier: Development Status :: 4 - Beta
Classifier: Intended Audience :: Developers
Classifier: Intended Audience :: Science/Research
Classifier: Operating System :: OS Independent
Classifier: Programming Language :: Python :: 3
Classifier: Programming Language :: Python :: 3.11
Classifier: Programming Language :: Python :: 3.12
Classifier: Topic :: Scientific/Engineering :: Artificial Intelligence
Classifier: Topic :: Database
Classifier: Topic :: Software Development :: Libraries :: Python Modules
Requires-Python: >=3.11
License-File: LICENSE
Requires-Dist: numpy>=1.24.0
Requires-Dist: pandas>=2.0.0
Requires-Dist: scikit-learn>=1.3.0
Requires-Dist: sentence-transformers>=2.2.0
Requires-Dist: torch>=2.0.0
Requires-Dist: transformers>=4.30.0
Requires-Dist: weaviate-client>=3.25.0
Requires-Dist: pylatexenc>=2.10
Requires-Dist: regex>=2023.0.0
Requires-Dist: nltk>=3.8.0
Requires-Dist: spacy>=3.6.0
Requires-Dist: markdown-it-py>=3.0.0
Requires-Dist: requests>=2.31.0
Requires-Dist: pyyaml>=6.0
Requires-Dist: pydantic>=2.0.0
Requires-Dist: python-dotenv>=1.0.0
Requires-Dist: html2text>=2020.1.16
Requires-Dist: email-reply-parser>=0.5.1
Requires-Dist: beautifulsoup4>=4.12.0
Provides-Extra: dev
Requires-Dist: pytest>=7.4.0; extra == "dev"
Requires-Dist: pytest-cov>=4.1.0; extra == "dev"
Requires-Dist: pytest-mock>=3.11.0; extra == "dev"
Requires-Dist: black>=23.0.0; extra == "dev"
Requires-Dist: flake8>=6.0.0; extra == "dev"
Requires-Dist: isort>=5.12.0; extra == "dev"
Requires-Dist: mypy>=1.5.0; extra == "dev"
Requires-Dist: pre-commit>=3.0.0; extra == "dev"
Provides-Extra: docs
Requires-Dist: mkdocs>=1.6.0; extra == "docs"
Requires-Dist: mkdocs-material>=9.5.0; extra == "docs"
Requires-Dist: mkdocstrings>=0.24.0; extra == "docs"
Requires-Dist: mkdocstrings-python>=1.10.0; extra == "docs"
Requires-Dist: mkdocs-autorefs>=1.0.0; extra == "docs"
Requires-Dist: pymdown-extensions>=10.0; extra == "docs"
Provides-Extra: jupyter
Requires-Dist: jupyter>=1.0.0; extra == "jupyter"
Requires-Dist: ipykernel>=6.25.0; extra == "jupyter"
Requires-Dist: notebook>=7.0.0; extra == "jupyter"
Dynamic: license-file
